PF23019UNO/_init_.py
PF23019UNO/metodos_lineales.py
PF23019UNO/metodos_no_lineales.py
pf23019uno-1.1.dist-info/METADATA
pf23019uno-1.1.dist-info/WHEEL
pf23019uno-1.1.dist-info/top_level.txt
pf23019uno-1.1.dist-info/RECORD
