Metadata-Version: 2.4
Name: PF23019UNO
Version: 1.1
Summary: Librería para resolver sistemas lineales y no lineales
Home-page: https://github.com/Jotade21/PF23019UNO.git
Author: Josue David Parada Flores
Author-email: PF23019@ues.edu.sv
Requires-Python: >=3.6
Requires-Dist: numpy
Dynamic: author
Dynamic: author-email
Dynamic: description
Dynamic: description-content-type
Dynamic: home-page
Dynamic: requires-dist
Dynamic: requires-python
Dynamic: summary
